pert_estimator/__init__.py
pert_estimator/__main__.py
pert_estimator/utils.py
pert_estimator-0.1.2.dist-info/LICENSE.txt
pert_estimator-0.1.2.dist-info/METADATA
pert_estimator-0.1.2.dist-info/WHEEL
pert_estimator-0.1.2.dist-info/entry_points.txt
pert_estimator-0.1.2.dist-info/top_level.txt
pert_estimator-0.1.2.dist-info/RECORD
