Metadata-Version: 2.1
Name: pert-estimator
Version: 0.1.2
Summary: PERT estimation tool
Home-page: https://github.com/andrewdieken/pert_estimator
Author: Andrew Dieken
Author-email: andrewrd@live.com
License: MIT
Keywords: pert,estimator,ticket,story
Platform: UNKNOWN
Classifier: Development Status :: 5 - Production/Stable
Classifier: Intended Audience :: Developers
Classifier: License :: OSI Approved :: MIT License
Classifier: Operating System :: OS Independent
Classifier: Programming Language :: Python :: 3
Classifier: Programming Language :: Python :: 3.4
Classifier: Programming Language :: Python :: 3.5
Classifier: Programming Language :: Python :: 3.6
Classifier: Programming Language :: Python :: 3.7
Requires-Dist: prettytable
